graphrag/__init__.py
graphrag/config/__init__.py
graphrag/config/create_graphrag_config.py
graphrag/config/defaults.py
graphrag/config/enums.py
graphrag/config/environment_reader.py
graphrag/config/errors.py
graphrag/config/input_models/__init__.py
graphrag/config/input_models/cache_config_input.py
graphrag/config/input_models/chunking_config_input.py
graphrag/config/input_models/claim_extraction_config_input.py
graphrag/config/input_models/cluster_graph_config_input.py
graphrag/config/input_models/community_reports_config_input.py
graphrag/config/input_models/embed_graph_config_input.py
graphrag/config/input_models/entity_extraction_config_input.py
graphrag/config/input_models/global_search_config_input.py
graphrag/config/input_models/graphrag_config_input.py
graphrag/config/input_models/input_config_input.py
graphrag/config/input_models/llm_config_input.py
graphrag/config/input_models/llm_parameters_input.py
graphrag/config/input_models/local_search_config_input.py
graphrag/config/input_models/parallelization_parameters_input.py
graphrag/config/input_models/reporting_config_input.py
graphrag/config/input_models/snapshots_config_input.py
graphrag/config/input_models/storage_config_input.py
graphrag/config/input_models/summarize_descriptions_config_input.py
graphrag/config/input_models/text_embedding_config_input.py
graphrag/config/input_models/umap_config_input.py
graphrag/config/models/__init__.py
graphrag/config/models/cache_config.py
graphrag/config/models/chunking_config.py
graphrag/config/models/claim_extraction_config.py
graphrag/config/models/cluster_graph_config.py
graphrag/config/models/community_reports_config.py
graphrag/config/models/embed_graph_config.py
graphrag/config/models/entity_extraction_config.py
graphrag/config/models/global_search_config.py
graphrag/config/models/graph_rag_config.py
graphrag/config/models/input_config.py
graphrag/config/models/llm_config.py
graphrag/config/models/llm_parameters.py
graphrag_with_trace-0.3.4.dist-info/LICENSE
graphrag_with_trace-0.3.4.dist-info/METADATA
graphrag_with_trace-0.3.4.dist-info/WHEEL
graphrag_with_trace-0.3.4.dist-info/RECORD
