Metadata-Version: 2.1
Name: graphrag-with-trace
Version: 0.3.4
Summary: graphrag-with-trace
License: MIT
Author: huqianghui
Author-email: qiah@microsoft.com
Requires-Python: >=3.10,<3.13
Classifier: License :: OSI Approved :: MIT License
Classifier: Programming Language :: Python :: 3
Classifier: Programming Language :: Python :: 3.10
Classifier: Programming Language :: Python :: 3.11
Classifier: Programming Language :: Python :: 3.12
Requires-Dist: aiofiles (>=24.1.0,<25.0.0)
Requires-Dist: aiolimiter (>=1.1.0,<2.0.0)
Requires-Dist: azure-identity (>=1.17.1,<2.0.0)
Requires-Dist: azure-search-documents (>=11.4.0,<12.0.0)
Requires-Dist: azure-storage-blob (>=12.19.0,<13.0.0)
Requires-Dist: datashaper (>=0.0.49,<0.0.50)
Requires-Dist: devtools (>=0.12.2,<0.13.0)
Requires-Dist: environs (>=11.0.0,<12.0.0)
Requires-Dist: fastparquet (>=2024.2.0,<2025.0.0)
Requires-Dist: graspologic (>=3.4.1,<4.0.0)
Requires-Dist: json-repair (>=0.25.3,<0.26.0)
Requires-Dist: lancedb (>=0.11.0,<0.12.0)
Requires-Dist: nest-asyncio (>=1.6.0,<2.0.0) ; platform_system == "Windows"
Requires-Dist: networkx (>=3,<4)
Requires-Dist: nltk (==3.8.1)
Requires-Dist: numba (==0.60.0)
Requires-Dist: numpy (>=1.25.2,<2.0.0)
Requires-Dist: openai (>=1.37.1,<2.0.0)
Requires-Dist: promptflow (>=1.4.0,<2.0.0)
Requires-Dist: promptflow-tools (>=1.4.0,<2.0.0)
Requires-Dist: pyaml-env (>=1.2.1,<2.0.0)
Requires-Dist: pydantic (>=2,<3)
Requires-Dist: python-dotenv (>=1.0.0,<2.0.0)
Requires-Dist: pyyaml (>=6.0.1,<7.0.0)
Requires-Dist: rich (>=13.6.0,<14.0.0)
Requires-Dist: scipy (==1.12.0)
Requires-Dist: swifter (>=1.4.0,<2.0.0)
Requires-Dist: tenacity (>=8.5.0,<9.0.0)
Requires-Dist: textual (>=0.74.0,<0.75.0)
Requires-Dist: tiktoken (>=0.7.0,<0.8.0)
Requires-Dist: typing-extensions (>=4.12.2,<5.0.0)
Requires-Dist: uvloop (>=0.19.0,<0.20.0) ; platform_system != "Windows"
